stock_backtest/__init__.py
stock_backtest/stock_backtest.py
stock_backtest-0.1.1.dist-info/METADATA
stock_backtest-0.1.1.dist-info/WHEEL
stock_backtest-0.1.1.dist-info/top_level.txt
stock_backtest-0.1.1.dist-info/RECORD
